pyecoplug/__init__.py
pyecoplug/discovery.py
pyecoplug/plug.py
pyecoplug-0.0.5.dist-info/DESCRIPTION.rst
pyecoplug-0.0.5.dist-info/METADATA
pyecoplug-0.0.5.dist-info/RECORD
pyecoplug-0.0.5.dist-info/WHEEL
pyecoplug-0.0.5.dist-info/metadata.json
pyecoplug-0.0.5.dist-info/top_level.txt
pyecoplug-0.0.5.dist-info/zip-safe
