Metadata-Version: 2.0
Name: pyecoplug
Version: 0.0.5
Summary: Interface for the EcoPlug outlet
Home-page: http://github.com/philburr/pyecoplug
Author: phil.burr@gmail.com
Author-email: UNKNOWN
License: MIT
Platform: UNKNOWN
